caraml/__init__.py
caraml/inmemory/__init__.py
caraml/inmemory/inmemory.py
caraml/utils/__init__.py
caraml/utils/serializer.py
caraml/zmq/__init__.py
caraml/zmq/communicator.py
caraml/zmq/inmem_data_fetcher.py
caraml/zmq/proxy.py
caraml-0.10.0.dist-info/DESCRIPTION.rst
caraml-0.10.0.dist-info/METADATA
caraml-0.10.0.dist-info/RECORD
caraml-0.10.0.dist-info/WHEEL
caraml-0.10.0.dist-info/metadata.json
caraml-0.10.0.dist-info/top_level.txt
