Metadata-Version: 2.0
Name: caraml
Version: 0.10.0
Summary: Carefree Accelerated Messaging Library: protocol layer for distributed machine learning
Home-page: https://github.com/SurrealAI/caraml
Author: Surreal AI team
Author-email: UNKNOWN
License: GPLv3
Keywords: Distributed,Messaging,Machine Learning
Platform: UNKNOWN
Classifier: Development Status :: 4 - Beta
Classifier: Environment :: Console
Classifier: Programming Language :: Python :: 3
Requires-Python: >=3.5
Requires-Dist: pyarrow
Requires-Dist: nanolog
Requires-Dist: zmq
